my_semantic_analyzer/__init__.py
my_semantic_analyzer/semantic_analyzer.py
my_semantic_analyzer-0.1.0.dist-info/licenses/LICENSE.txt
my_semantic_analyzer-0.1.0.dist-info/METADATA
my_semantic_analyzer-0.1.0.dist-info/WHEEL
my_semantic_analyzer-0.1.0.dist-info/top_level.txt
my_semantic_analyzer-0.1.0.dist-info/RECORD
