Metadata-Version: 2.4
Name: my_semantic_analyzer
Version: 0.1.0
Summary: A semantic analyzer package
Author: Your Name
Requires-Python: >=3.7
License-File: LICENSE.txt
Dynamic: author
Dynamic: license-file
Dynamic: requires-python
Dynamic: summary
